{"frameRate":24,"name":"chuizidj","version":"5.5","compatibleVersion":"5.5","armature":[{"type":"Sheet","frameRate":10,"name":"chuizidj","aabb":{"x":-128,"y":-128,"width":256,"height":256},"bone":[{"name":"root"}],"slot":[{"displayIndex":9,"name":"sheetSlot","parent":"root"}],"skin":[{"slot":[{"name":"sheetSlot","display":[{"name":"锤子_00005"},{"name":"锤子_00006"},{"name":"锤子_00007"},{"name":"锤子_00008"},{"name":"锤子_00009"},{"name":"锤子_00000"},{"name":"锤子_00001"},{"name":"锤子_00002"},{"name":"锤子_00003"},{"name":"锤子_00004"}]}]}],"animation":[{"duration":10,"playTimes":0,"name":"chuizidj","slot":[{"name":"sheetSlot","displayFrame":[{},{"value":1},{"value":2},{"value":3},{"value":4},{"value":5},{"value":6},{"value":7},{"value":8},{"value":9}]}]}],"defaultActions":[{"gotoAndPlay":"chuizidj"}]}]}